{
    "files": ["a", "b", "c", "d", "e", "f", "g", "h"],
    "ranks": ["1", "2", "3", "4", "5", "6", "7", "8"],
    "pieces": {
    
        "d1": {"name": "q", "color": "w"},
        
        "a8": {"name": "r", "color": "b"},
        "b8": {"name": "n", "color": "b"},
        "c8": {"name": "b", "color": "b"},
        "d8": {"name": "q", "color": "b"},
        "e8": {"name": "k", "color": "b"},
        "f8": {"name": "b", "color": "b"},
        "g8": {"name": "n", "color": "b"},
        "h8": {"name": "r", "color": "b"},
        "a7": {"name": "p", "color": "b"},
        "b7": {"name": "p", "color": "b"},
        "c7": {"name": "p", "color": "b"},
        "d7": {"name": "p", "color": "b"},
        "e7": {"name": "p", "color": "b"},
        "f7": {"name": "p", "color": "b"},
        "g7": {"name": "p", "color": "b"},
        "h7": {"name": "p", "color": "b"}
    }
}
